{
"update":
[
{
"type":"string",
"key":"SessionNumber",
"value":"SM190010-TRF-DEMO-461"
} , {
"type":"string",
"key":"AccountID",
"value":"A100096"
}
],
"rows":
[
{
"Camera ID":"SM190010-TRF-DEMO",
"SessionNumber":"SM190010-TRF-DEMO-461",
"AccountID":"A100096",
"Distance":"60",
"Target Type":"Game Mode",
"PitchNumber":1,
"X":"Y",
"Y":8,
"Date":"2019-08-25T18:04:08",
"Time":"2019-08-25T18:04:08",
"MPH":"54.0",
"MPH Plate Speed":"54.0",
"MPH Release":"57.0",
"Call":"MISS",
"Call":"MISS",
"X":"Y",
"Y":8,
"EI Row ID":"SM190010-TRF-DEMO-461-1",
"EI Row Count":"1"
}
,{
"Camera ID":"SM190010-TRF-DEMO",
"SessionNumber":"SM190010-TRF-DEMO-461",
"AccountID":"A100096",
"Distance":"60",
"Target Type":"Game Mode",
"PitchNumber":2,
"X":"H",
"Y":16,
"Date":"2019-08-25T18:04:48",
"Time":"2019-08-25T18:04:48",
"MPH":"53.0",
"MPH Plate Speed":"53.0",
"MPH Release":"56.0",
"Call":"MISS",
"Call":"MISS",
"X":"H",
"Y":16,
"EI Row ID":"SM190010-TRF-DEMO-461-2",
"EI Row Count":"1"
}
,{
"Camera ID":"SM190010-TRF-DEMO",
"SessionNumber":"SM190010-TRF-DEMO-461",
"AccountID":"A100096",
"Distance":"60",
"Target Type":"Game Mode",
"PitchNumber":3,
"X":"K",
"Y":19,
"Date":"2019-08-25T18:05:06",
"Time":"2019-08-25T18:05:06",
"MPH":"53.0",
"MPH Plate Speed":"53.0",
"MPH Release":"56.0",
"Call":"MISS",
"Call":"MISS",
"X":"K",
"Y":19,
"EI Row ID":"SM190010-TRF-DEMO-461-3",
"EI Row Count":"1"
}
,{
"Camera ID":"SM190010-TRF-DEMO",
"SessionNumber":"SM190010-TRF-DEMO-461",
"AccountID":"A100096",
"Distance":"60",
"Target Type":"Game Mode",
"PitchNumber":4,
"X":"R",
"Y":25,
"Date":"2019-08-25T18:05:31",
"Time":"2019-08-25T18:05:31",
"MPH":"55.0",
"MPH Plate Speed":"55.0",
"MPH Release":"58.0",
"Call":"MISS",
"Call":"MISS",
"X":"R",
"Y":25,
"EI Row ID":"SM190010-TRF-DEMO-461-4",
"EI Row Count":"1"
}
,{
"Camera ID":"SM190010-TRF-DEMO",
"SessionNumber":"SM190010-TRF-DEMO-461",
"AccountID":"A100096",
"Distance":"60",
"Target Type":"Game Mode",
"PitchNumber":5,
"X":"I",
"Y":15,
"Date":"2019-08-25T18:05:45",
"Time":"2019-08-25T18:05:45",
"MPH":"56.0",
"MPH Plate Speed":"56.0",
"MPH Release":"59.0",
"Call":"MISS",
"Call":"MISS",
"X":"I",
"Y":15,
"EI Row ID":"SM190010-TRF-DEMO-461-5",
"EI Row Count":"1"
}
,{
"Camera ID":"SM190010-TRF-DEMO",
"SessionNumber":"SM190010-TRF-DEMO-461",
"AccountID":"A100096",
"Distance":"60",
"Target Type":"Game Mode",
"PitchNumber":6,
"X":"P",
"Y":11,
"Date":"2019-08-25T18:05:57",
"Time":"2019-08-25T18:05:57",
"MPH":"59.0",
"MPH Plate Speed":"59.0",
"MPH Release":"62.0",
"Call":"SUCCESS",
"Call":"SUCCESS",
"X":"P",
"Y":11,
"EI Row ID":"SM190010-TRF-DEMO-461-6",
"EI Row Count":"1"
}
,{
"Camera ID":"SM190010-TRF-DEMO",
"SessionNumber":"SM190010-TRF-DEMO-461",
"AccountID":"A100096",
"Distance":"60",
"Target Type":"Game Mode",
"PitchNumber":7,
"X":"S",
"Y":24,
"Date":"2019-08-25T18:06:38",
"Time":"2019-08-25T18:06:38",
"MPH":"58.0",
"MPH Plate Speed":"58.0",
"MPH Release":"61.0",
"Call":"SUCCESS",
"Call":"SUCCESS",
"X":"S",
"Y":24,
"EI Row ID":"SM190010-TRF-DEMO-461-7",
"EI Row Count":"1"
}
,{
"Camera ID":"SM190010-TRF-DEMO",
"SessionNumber":"SM190010-TRF-DEMO-461",
"AccountID":"A100096",
"Distance":"60",
"Target Type":"Game Mode",
"PitchNumber":8,
"X":"J",
"Y":10,
"Date":"2019-08-25T18:06:52",
"Time":"2019-08-25T18:06:52",
"MPH":"57.0",
"MPH Plate Speed":"57.0",
"MPH Release":"60.0",
"Call":"SUCCESS",
"Call":"SUCCESS",
"X":"J",
"Y":10,
"EI Row ID":"SM190010-TRF-DEMO-461-8",
"EI Row Count":"1"
}
,{
"Camera ID":"SM190010-TRF-DEMO",
"SessionNumber":"SM190010-TRF-DEMO-461",
"AccountID":"A100096",
"Distance":"60",
"Target Type":"Game Mode",
"PitchNumber":9,
"X":"M",
"Y":23,
"Date":"2019-08-25T18:07:05",
"Time":"2019-08-25T18:07:05",
"MPH":"61.0",
"MPH Plate Speed":"61.0",
"MPH Release":"64.0",
"Call":"MISS",
"Call":"MISS",
"X":"M",
"Y":23,
"EI Row ID":"SM190010-TRF-DEMO-461-9",
"EI Row Count":"1"
}
,{
"Camera ID":"SM190010-TRF-DEMO",
"SessionNumber":"SM190010-TRF-DEMO-461",
"AccountID":"A100096",
"Distance":"60",
"Target Type":"Game Mode",
"PitchNumber":10,
"X":"T",
"Y":17,
"Date":"2019-08-25T18:07:20",
"Time":"2019-08-25T18:07:20",
"MPH":"57.0",
"MPH Plate Speed":"57.0",
"MPH Release":"60.0",
"Call":"MISS",
"Call":"MISS",
"X":"T",
"Y":17,
"EI Row ID":"SM190010-TRF-DEMO-461-10",
"EI Row Count":"1"
}
,{
"Camera ID":"SM190010-TRF-DEMO",
"SessionNumber":"SM190010-TRF-DEMO-461",
"AccountID":"A100096",
"Distance":"60",
"Target Type":"Game Mode",
"PitchNumber":11,
"X":"J",
"Y":11,
"Date":"2019-08-25T18:07:49",
"Time":"2019-08-25T18:07:49",
"MPH":"62.0",
"MPH Plate Speed":"62.0",
"MPH Release":"65.0",
"Call":"SUCCESS",
"Call":"SUCCESS",
"X":"J",
"Y":11,
"EI Row ID":"SM190010-TRF-DEMO-461-11",
"EI Row Count":"1"
}
,{
"Camera ID":"SM190010-TRF-DEMO",
"SessionNumber":"SM190010-TRF-DEMO-461",
"AccountID":"A100096",
"Distance":"60",
"Target Type":"Game Mode",
"PitchNumber":12,
"X":"U",
"Y":20,
"Date":"2019-08-25T18:08:03",
"Time":"2019-08-25T18:08:03",
"MPH":"57.0",
"MPH Plate Speed":"57.0",
"MPH Release":"60.0",
"Call":"SUCCESS",
"Call":"SUCCESS",
"X":"U",
"Y":20,
"EI Row ID":"SM190010-TRF-DEMO-461-12",
"EI Row Count":"1"
}
,{
"Camera ID":"SM190010-TRF-DEMO",
"SessionNumber":"SM190010-TRF-DEMO-461",
"AccountID":"A100096",
"Distance":"60",
"Target Type":"Game Mode",
"PitchNumber":13,
"X":"H",
"Y":15,
"Date":"2019-08-25T18:08:17",
"Time":"2019-08-25T18:08:17",
"MPH":"59.0",
"MPH Plate Speed":"59.0",
"MPH Release":"62.0",
"Call":"MISS",
"Call":"MISS",
"X":"H",
"Y":15,
"EI Row ID":"SM190010-TRF-DEMO-461-13",
"EI Row Count":"1"
}
]
}
